LICENSE.txt
MANIFEST.in
README.md
setup.cfg
setup.py
pm20_3/__init__.py
pm20_3/questions.py
pm20_3.egg-info/PKG-INFO
pm20_3.egg-info/SOURCES.txt
pm20_3.egg-info/dependency_links.txt
pm20_3.egg-info/requires.txt
pm20_3.egg-info/top_level.txt
pm20_3/__pycache__/__init__.cpython-39.pyc
pm20_3/__pycache__/questions.cpython-39.pyc
pm20_3/q/__init__.py
pm20_3/q/q_1.png
pm20_3/q/q_100_1.png
pm20_3/q/q_100_2.png
pm20_3/q/q_101.png
pm20_3/q/q_102_1.png
pm20_3/q/q_102_2.png
pm20_3/q/q_103.png
pm20_3/q/q_104.png
pm20_3/q/q_105.png
pm20_3/q/q_106.png
pm20_3/q/q_107.png
pm20_3/q/q_108.png
pm20_3/q/q_109_1.png
pm20_3/q/q_109_2.png
pm20_3/q/q_10_1.png
pm20_3/q/q_10_2.png
pm20_3/q/q_110.png
pm20_3/q/q_111_1.png
pm20_3/q/q_111_2.png
pm20_3/q/q_112.png
pm20_3/q/q_113.png
pm20_3/q/q_114_1.png
pm20_3/q/q_114_2.png
pm20_3/q/q_115.png
pm20_3/q/q_116.png
pm20_3/q/q_117.png
pm20_3/q/q_118_1.png
pm20_3/q/q_118_2.png
pm20_3/q/q_119.png
pm20_3/q/q_11_1.png
pm20_3/q/q_11_2.png
pm20_3/q/q_120.png
pm20_3/q/q_121.png
pm20_3/q/q_12_1.png
pm20_3/q/q_12_2.png
pm20_3/q/q_13_1.png
pm20_3/q/q_13_2.png
pm20_3/q/q_14.png
pm20_3/q/q_15.png
pm20_3/q/q_16.png
pm20_3/q/q_17.png
pm20_3/q/q_18.png
pm20_3/q/q_19.png
pm20_3/q/q_2.png
pm20_3/q/q_20.png
pm20_3/q/q_21.png
pm20_3/q/q_22.png
pm20_3/q/q_23.png
pm20_3/q/q_24.png
pm20_3/q/q_25.png
pm20_3/q/q_26.png
pm20_3/q/q_27.png
pm20_3/q/q_28_1.png
pm20_3/q/q_28_2.png
pm20_3/q/q_28_3.png
pm20_3/q/q_29.png
pm20_3/q/q_30.png
pm20_3/q/q_31.png
pm20_3/q/q_32.png
pm20_3/q/q_33.png
pm20_3/q/q_34.png
pm20_3/q/q_35.png
pm20_3/q/q_36.png
pm20_3/q/q_37.png
pm20_3/q/q_38.png
pm20_3/q/q_39.png
pm20_3/q/q_3_1.png
pm20_3/q/q_3_2.png
pm20_3/q/q_40.png
pm20_3/q/q_41.png
pm20_3/q/q_42.png
pm20_3/q/q_43.png
pm20_3/q/q_44.png
pm20_3/q/q_45_1.png
pm20_3/q/q_45_2.png
pm20_3/q/q_46_1.png
pm20_3/q/q_46_2.png
pm20_3/q/q_47.png
pm20_3/q/q_48.png
pm20_3/q/q_49.png
pm20_3/q/q_4_1.png
pm20_3/q/q_4_2.png
pm20_3/q/q_50.png
pm20_3/q/q_51.png
pm20_3/q/q_52.png
pm20_3/q/q_53.png
pm20_3/q/q_54.png
pm20_3/q/q_55.png
pm20_3/q/q_56.png
pm20_3/q/q_57.png
pm20_3/q/q_58.png
pm20_3/q/q_59.png
pm20_3/q/q_5_1.png
pm20_3/q/q_5_2.png
pm20_3/q/q_6.png
